pyxtension/Json.py
pyxtension/__init__.py
pyxtension/__models.py
pyxtension/fileutils.py
pyxtension/mockutils.py
pyxtension/models.py
pyxtension/racelib.py
pyxtension/safe_dict.py
pyxtension/streams.py
pyxtension/throttler.py
pyxtension-1.17.1.data/data/requirements.txt
pyxtension-1.17.1.dist-info/LICENSE
pyxtension-1.17.1.dist-info/METADATA
pyxtension-1.17.1.dist-info/WHEEL
pyxtension-1.17.1.dist-info/top_level.txt
pyxtension-1.17.1.dist-info/RECORD
