Metadata-Version: 2.2
Name: pyxtension
Version: 1.17.1
Summary: Extension library for Python
Home-page: https://github.com/asuiu/pyxtension
Author: Andrei Suiu
Author-email: andrei.suiu@gmail.com
Classifier: Development Status :: 5 - Production/Stable
Classifier: Intended Audience :: Developers
Classifier: Programming Language :: Python :: 3.8
Classifier: Programming Language :: Python :: 3.9
Classifier: Programming Language :: Python :: 3.10
Classifier: Programming Language :: Python :: 3.11
Classifier: Programming Language :: Python :: Implementation :: CPython
Classifier: Programming Language :: Python :: Implementation :: PyPy
Requires-Python: >=3.8, <4
License-File: LICENSE
Requires-Dist: json-composite-encoder>=1.0.0
Requires-Dist: pydantic>=1.8.2; python_version >= "3"
Requires-Dist: streamerate>=1.1.4
Requires-Dist: tblib>=1.7.0; python_version >= "3"
Requires-Dist: throttlex>=1.0.0
Requires-Dist: tqdm>=4.62.0; python_version >= "3"
Provides-Extra: dev
Requires-Dist: numpy>=1.22.2; extra == "dev"
Requires-Dist: pandas>=1.0.3; extra == "dev"
Requires-Dist: pre-commit>=2.20.0; extra == "dev"
Requires-Dist: prospector>=1.10.3; extra == "dev"
Requires-Dist: tsx>=0.0.1; extra == "dev"
Requires-Dist: twine>=4.0.1; extra == "dev"
Provides-Extra: test
Requires-Dist: numpy>=1.22.2; extra == "test"
Requires-Dist: pandas>=1.0.3; extra == "test"
Requires-Dist: pre-commit>=2.20.0; extra == "test"
Requires-Dist: prospector>=1.10.3; extra == "test"
Requires-Dist: tsx>=0.0.1; extra == "test"
Requires-Dist: twine>=4.0.1; extra == "test"
Dynamic: author
Dynamic: author-email
Dynamic: classifier
Dynamic: description
Dynamic: description-content-type
Dynamic: home-page
Dynamic: provides-extra
Dynamic: requires-dist
Dynamic: requires-python
Dynamic: summary
